ethicml/__init__.py
ethicml/common.py
ethicml/data/__init__.py
ethicml/data/csvs/UCI_Credit_Card.csv
ethicml/data/csvs/__init__.py
ethicml/data/csvs/admissions.csv.zip
ethicml/data/csvs/adult.csv.zip
ethicml/data/csvs/adult_old.csv
ethicml/data/csvs/celeba.csv.zip
ethicml/data/csvs/compas-recidivism.csv
ethicml/data/csvs/crime.csv
ethicml/data/csvs/genfaces.csv.zip
ethicml/data/csvs/german.csv
ethicml/data/csvs/health.csv.zip
ethicml/data/csvs/law.csv.zip
ethicml/data/csvs/lipton.csv
ethicml/data/csvs/make_admissions_from_raw.py
ethicml/data/csvs/make_adult_from_raw.py
ethicml/data/csvs/make_crime_from_raw.py
ethicml/data/csvs/make_health_from_raw.py
ethicml/data/csvs/make_law.py
ethicml/data/csvs/make_lipton.py
ethicml/data/csvs/make_non_binary_toy.py
ethicml/data/csvs/make_nursery.py
ethicml/data/csvs/make_synthetic_1.py
ethicml/data/csvs/make_synthetic_2.py
ethicml/data/csvs/make_synthetic_3.py
ethicml/data/csvs/make_synthetic_4.py
ethicml/data/csvs/make_toy_dataset.py
ethicml/data/csvs/nbt.csv
ethicml/data/csvs/non-binary-toy.csv
ethicml/data/csvs/nursery.csv.zip
ethicml/data/csvs/sqf.csv
ethicml/data/csvs/synthetic_scenario_1.csv
ethicml/data/csvs/synthetic_scenario_2.csv
ethicml/data/csvs/synthetic_scenario_3.csv
ethicml/data/csvs/synthetic_scenario_4.csv
ethicml/data/csvs/toy.csv
ethicml/data/csvs/toy_old.csv
ethicml/data/csvs/utility.py
ethicml/data/dataset.py
ethicml/data/load.py
ethicml/data/lookup.py
ethicml/data/tabular_data/__init__.py
ethicml/data/tabular_data/acs.py
ethicml/data/tabular_data/admissions.py
ethicml/data/tabular_data/adult.py
ethicml/data/tabular_data/compas.py
ethicml/data/tabular_data/credit.py
ethicml/data/tabular_data/crime.py
ethicml/data/tabular_data/german.py
ethicml/data/tabular_data/health.py
ethicml/data/tabular_data/law.py
ethicml/data/tabular_data/lipton.py
ethicml/data/tabular_data/non_binary_toy.py
ethicml/data/tabular_data/nursery.py
ethicml/data/tabular_data/sqf.py
ethicml/data/tabular_data/synthetic.py
ethicml-1.3.0.dist-info/LICENSE
ethicml-1.3.0.dist-info/METADATA
ethicml-1.3.0.dist-info/WHEEL
ethicml-1.3.0.dist-info/RECORD
