Metadata-Version: 2.1
Name: EthicML
Version: 1.3.0
Summary: EthicML is a library for performing and assessing algorithmic fairness. Unlike other libraries, EthicML isn't an education tool, but rather a researcher's toolkit.
Home-page: https://github.com/wearepal/EthicML
Keywords: ml,fairness
Author: PAL
Author-email: info@wearepal.ai
Requires-Python: >=3.10,<3.13
Classifier: License :: OSI Approved :: GNU General Public License v3 (GPLv3)
Classifier: Operating System :: OS Independent
Classifier: Programming Language :: Python :: 3
Classifier: Programming Language :: Python :: 3.10
Classifier: Programming Language :: Python :: 3.11
Classifier: Programming Language :: Python :: 3.12
Classifier: Typing :: Typed
Provides-Extra: all
Provides-Extra: data
Provides-Extra: metrics
Provides-Extra: models
Provides-Extra: plot
Requires-Dist: GitPython (>=3.1.20,<4.0.0) ; extra == "models" or extra == "all"
Requires-Dist: cloudpickle (>=2.0.0,<3.0.0) ; extra == "models" or extra == "all"
Requires-Dist: fairlearn (==0.8.0) ; extra == "models" or extra == "all"
Requires-Dist: filelock
Requires-Dist: folktables (>=0.0.12) ; extra == "data" or extra == "all"
Requires-Dist: gitdb2 (==4.0.2) ; extra == "models" or extra == "all"
Requires-Dist: jinja2
Requires-Dist: joblib (>=1.1.0,<2.0.0)
Requires-Dist: matplotlib (>=3.8) ; extra == "plot" or extra == "all"
Requires-Dist: networkx
Requires-Dist: numpy (>=1.23.2)
Requires-Dist: pandas (>=1.5.0)
Requires-Dist: pdm (>=2.4.0,<3.0.0) ; extra == "models" or extra == "all"
Requires-Dist: pillow (>=8.4.0)
Requires-Dist: ranzen (>=2.0.1,<3.0.0,!=2.1.0)
Requires-Dist: requests
Requires-Dist: scikit-learn (>=0.20.1) ; extra == "metrics" or extra == "models" or extra == "all"
Requires-Dist: scipy (>=1.7.2,<2.0.0) ; extra == "models" or extra == "all"
Requires-Dist: seaborn (>=0.9.0) ; extra == "plot" or extra == "all"
Requires-Dist: smmap2 (==3.0.1) ; extra == "models" or extra == "all"
Requires-Dist: sympy (>=1.12,<2.0)
Requires-Dist: teext (>=0.1.3,<0.2.0)
Requires-Dist: typing-extensions (>=4.5)
Project-URL: Repository, https://github.com/wearepal/EthicML
